Metadata-Version: 1.0
Name: CC-probability
Version: 1.0
Summary: Gaussian and Binomial Distributions
Home-page: UNKNOWN
Author: UNKNOWN
Author-email: UNKNOWN
License: UNKNOWN
Platform: UNKNOWN
